LICENSE
README.md
setup.py
exodus_core/__init__.py
exodus_core.egg-info/PKG-INFO
exodus_core.egg-info/SOURCES.txt
exodus_core.egg-info/dependency_links.txt
exodus_core.egg-info/not-zip-safe
exodus_core.egg-info/requires.txt
exodus_core.egg-info/top_level.txt
exodus_core/analysis/__init__.py
exodus_core/analysis/apk_signature.py
exodus_core/analysis/certificate.py
exodus_core/analysis/static_analysis.py
exodus_core/analysis/test_exodus_analyze.py
exodus_core/analysis/utils.py
exodus_core/helper/__init__.py
exodus_core/helper/connector.py