Metadata-Version: 2.1
Name: exodus-core
Version: 1.3.10
Summary: Core functionality of εxodus
Home-page: https://github.com/Exodus-Privacy/exodus-core
Author: Exodus Privacy
Author-email: contact@exodus-privacy.eu.org
License: UNKNOWN
Platform: UNKNOWN
License-File: LICENSE
